target_duckdb/__init__.py
target_duckdb/db_sync.py
target_duckdb/logger.py
target_duckdb/logging.conf
target_duckdb-0.8.0.dist-info/LICENSE
target_duckdb-0.8.0.dist-info/METADATA
target_duckdb-0.8.0.dist-info/WHEEL
target_duckdb-0.8.0.dist-info/entry_points.txt
target_duckdb-0.8.0.dist-info/top_level.txt
target_duckdb-0.8.0.dist-info/RECORD
