Metadata-Version: 2.1
Name: target-duckdb
Version: 0.8.0
Summary: Singer.io target for loading data into DuckDB
Home-page: https://github.com/jwills/target-duckdb
Author: Josh Wills
Classifier: License :: OSI Approved :: Apache Software License
Classifier: Programming Language :: Python :: 3 :: Only
License-File: LICENSE
Requires-Dist: jsonschema>=3.2.0
Requires-Dist: duckdb>=1.0.0
Provides-Extra: test
Requires-Dist: pytest; extra == "test"
Requires-Dist: pylint; extra == "test"
Requires-Dist: pytest-cov; extra == "test"
